iamtokenizing/__init__.py
iamtokenizing/base_tokenizer.py
iamtokenizing/chargrams.py
iamtokenizing/context_detector.py
iamtokenizing/ngrams.py
iamtokenizing/regex_detector.py
iamtokenizing-0.6.2.dist-info/LICENSE
iamtokenizing-0.6.2.dist-info/METADATA
iamtokenizing-0.6.2.dist-info/WHEEL
iamtokenizing-0.6.2.dist-info/top_level.txt
iamtokenizing-0.6.2.dist-info/RECORD
