Metadata-Version: 2.1
Name: iamtokenizing
Version: 0.6.2
Summary: Simple tokenizers: n-grams and chargrams splitting, white space splitting, or splitting using configurable REGEX expression, or detection into context tokenization. Based on Span and Token objects from the tokenspan package.
Home-page: https://framagit.org/nlp/iamtokenizing/
Author: IAM CHU Bordeaux France
Author-email: via.issue@only.please
License: GNU GENERAL PUBLIC LICENSE v.3
Platform: UNKNOWN
Classifier: Programming Language :: Python :: 3
Classifier: License :: OSI Approved :: GNU General Public License v3 (GPLv3)
Classifier: Operating System :: OS Independent
Classifier: Topic :: Scientific/Engineering :: Information Analysis
Classifier: Topic :: Text Processing
Classifier: Intended Audience :: Information Technology
Classifier: Intended Audience :: Science/Research
Requires-Python: >=3.7
License-File: LICENSE
Requires-Dist: tokenspan (>=0.7.1)
